{
	"name": "Source",
	"properties": {
		"linkedServiceName": {
			"referenceName": "Git",
			"type": "LinkedServiceReference"
		},
		"annotations": [],
		"type": "DelimitedText",
		"typeProperties": {
			"location": {
				"type": "AzureBlobStorageLocation",
				"fileName": "Empdata.csv",
				"container": "gitsource"
			},
			"columnDelimiter": ",",
			"escapeChar": "\\",
			"firstRowAsHeader": true,
			"quoteChar": "\""
		},
		"schema": [
			{
				"name": "EmpId",
				"type": "String"
			},
			{
				"name": "EmpName",
				"type": "String"
			},
			{
				"name": "PhNo",
				"type": "String"
			},
			{
				"name": "Salary",
				"type": "String"
			},
			{
				"name": "DeptID",
				"type": "String"
			}
		]
	}
}